synaptogen/__init__.py
synaptogen/default_params.json
synaptogen/synaptogen.py
synaptogen-0.2.0.dist-info/METADATA
synaptogen-0.2.0.dist-info/WHEEL
synaptogen-0.2.0.dist-info/licenses/LICENSE
synaptogen-0.2.0.dist-info/RECORD
