Metadata-Version: 2.3
Name: synaptogen
Version: 0.2.0
Summary: A fast generative model for stochastic memory cells
Project-URL: Homepage, https://github.com/thennen/Synaptogen.git/Synaptogen.py
Project-URL: Issues, https://github.com/thennen/Synaptogen/issues
Author-email: Tyler Hennen <tyler@hennen.us>
License-File: LICENSE
Classifier: License :: OSI Approved :: MIT License
Classifier: Operating System :: OS Independent
Classifier: Programming Language :: Python :: 3
Requires-Python: >=3.8
